odoo/addons/base_vat_required_vies/LICENSE
odoo/addons/base_vat_required_vies/README.rst
odoo/addons/base_vat_required_vies/__init__.py
odoo/addons/base_vat_required_vies/__manifest__.py
odoo/addons/base_vat_required_vies/i18n/de.po
odoo/addons/base_vat_required_vies/i18n/de_CH.po
odoo/addons/base_vat_required_vies/images/screen.png
odoo/addons/base_vat_required_vies/models/__init__.py
odoo/addons/base_vat_required_vies/models/res_partner.py
odoo/addons/base_vat_required_vies/static/description/icon.png
odoo/addons/base_vat_required_vies/static/description/index.html
odoo/addons/base_vat_required_vies/tests/TEST_INSTRUCTIONS.rst
odoo_addon_base_vat_required_vies-16.0.1.1.0.dist-info/METADATA
odoo_addon_base_vat_required_vies-16.0.1.1.0.dist-info/WHEEL
odoo_addon_base_vat_required_vies-16.0.1.1.0.dist-info/top_level.txt
odoo_addon_base_vat_required_vies-16.0.1.1.0.dist-info/RECORD
