Metadata-Version: 2.1
Name: odoo-addon-base_vat_required_vies
Version: 16.0.1.1.0
Requires-Python: >=3.10
Requires-Dist: odoo>=16.0a,<16.1dev
Summary: Make VIES VAT check mandatory.
Home-page: https://www.mint-system.ch/
License: AGPL-3
Author: Mint System GmbH
Classifier: Programming Language :: Python
Classifier: Framework :: Odoo
Classifier: Framework :: Odoo :: 16.0
Classifier: License :: OSI Approved :: GNU Affero General Public License v3
